[
    {
        "Numero Sind": 1,
        "Candidato Sindaco": "DE DOMENICO FRANCESCO DETTO FRANCO",
        "Voti validi": 22365,
        "Voti solo Sind": 0
    },
    {
        "Numero Sind": 2,
        "Candidato Sindaco": "STURNIOLO LUIGI DETTO GINO",
        "Voti validi": 1586,
        "Voti solo Sind": 0
    },
    {
        "Numero Sind": 3,
        "Candidato Sindaco": "TOTARO SALVATORE",
        "Voti validi": 2118,
        "Voti solo Sind": 0
    },
    {
        "Numero Sind": 4,
        "Candidato Sindaco": "BASILE FEDERICO",
        "Voti validi": 44392,
        "Voti solo Sind": 0
    },
    {
        "Numero Sind": 5,
        "Candidato Sindaco": "CROCE MAURIZIO",
        "Voti validi": 27187,
        "Voti solo Sind": 0
    }
]